LICENSE
MANIFEST.in
README
README.md
gpl-3.0.txt
setup.py
rocket/__init__.py
rocket/__main__.py
rocket/daisy/__init__.py
rocket/daisy/config
rocket/daisy/daisy-passwd.py
rocket/daisy/daisy.sh
rocket/daisy/daisy_setup.sh
rocket/daisy/passwd
rocket/daisy/clients/__init__.py
rocket/daisy/decorators/__init__.py
rocket/daisy/decorators/rest.py
rocket/daisy/devices/__init__.py
rocket/daisy/devices/bus.py
rocket/daisy/devices/i2c.py
rocket/daisy/devices/instance.py
rocket/daisy/devices/manager.py
rocket/daisy/devices/onewire.py
rocket/daisy/devices/serial.py
rocket/daisy/devices/spi.py
rocket/daisy/devices/analog/__init__.py
rocket/daisy/devices/analog/ads1x1x.py
rocket/daisy/devices/analog/mcp3x0x.py
rocket/daisy/devices/analog/mcp4725.py
rocket/daisy/devices/analog/mcp48XX.py
rocket/daisy/devices/analog/mcp492X.py
rocket/daisy/devices/analog/pca9685.py
rocket/daisy/devices/analog/pcf8591.py
rocket/daisy/devices/digital/__init__.py
rocket/daisy/devices/digital/ds2408.py
rocket/daisy/devices/digital/gpio.py
rocket/daisy/devices/digital/mcp23XXX.py
rocket/daisy/devices/digital/pcf8574.py
rocket/daisy/devices/sensor/__init__.py
rocket/daisy/devices/sensor/bmp085.py
rocket/daisy/devices/sensor/hytXXX.py
rocket/daisy/devices/sensor/onewiretemp.py
rocket/daisy/devices/sensor/tmpXXX.py
rocket/daisy/devices/sensor/tslXXXX.py
rocket/daisy/devices/sensor/vcnl4000.py
rocket/daisy/devices/shield/__init__.py
rocket/daisy/devices/shield/piface.py
rocket/daisy/htdocs/daisy.css
rocket/daisy/htdocs/daisy.js
rocket/daisy/htdocs/index.html
rocket/daisy/htdocs/jquery-ui.css
rocket/daisy/htdocs/jquery-ui.js
rocket/daisy/htdocs/jquery.js
rocket/daisy/protocols/__init__.py
rocket/daisy/protocols/coap.py
rocket/daisy/protocols/http.py
rocket/daisy/protocols/rest.py
rocket/daisy/server/__init__.py
rocket/daisy/utils/__init__.py
rocket/daisy/utils/config.py
rocket/daisy/utils/crypto.py
rocket/daisy/utils/loader.py
rocket/daisy/utils/logger.py
rocket/daisy/utils/thread.py
rocket_daisy.egg-info/PKG-INFO
rocket_daisy.egg-info/SOURCES.txt
rocket_daisy.egg-info/dependency_links.txt
rocket_daisy.egg-info/not-zip-safe
rocket_daisy.egg-info/top_level.txt
