Metadata-Version: 2.1
Name: rocket-daisy
Version: 1.1
Summary: Remote open control key enabling technology (Rocket)
Home-page: https://github.com/gulliversoft/motion
Author: gulliversoft
Author-email: df6@gulliversoft.com
License: GPL3
Platform: UNKNOWN
Classifier: Intended Audience :: Education
Classifier: Development Status :: 5 - Production/Stable
Classifier: Programming Language :: Python :: 3
Classifier: Operating System :: POSIX :: Linux
Classifier: Topic :: Software Development
Classifier: Topic :: Home Automation
Classifier: Topic :: System :: Hardware
